sds/__init__.py
sds/__main__.py
sds/classparams.py
sds/cli.py
sds/config.py
sds/dns.py
sds/dns_rr.py
sds/ipam.py
sds/ipam_ip.py
sds/ipam_network.py
sds/ipam_space.py
sds/server.py
solidservercli-0.6.1.dist-info/licenses/LICENSE
solidservercli-0.6.1.dist-info/METADATA
solidservercli-0.6.1.dist-info/WHEEL
solidservercli-0.6.1.dist-info/entry_points.txt
solidservercli-0.6.1.dist-info/top_level.txt
solidservercli-0.6.1.dist-info/RECORD
