Metadata-Version: 2.4
Name: SOLIDserverCLI
Version: 0.6.1
Summary: EfficientIP SOLIDserver cli
Home-page: https://gitlab.com/efficientip/cli-for-solidserver
Author: Alex Chauvin
Author-email: ach@efficientip.com
License: BSD 2-Clause License
Project-URL: GitHub, https://gitlab.com/efficientip/cli-for-solidserver
Project-URL: Changelog, https://gitlab.com/efficientip/cli-for-solidserver/-/raw/master/CHANGELOG.md
Classifier: Development Status :: 3 - Alpha
Classifier: Environment :: Console
Classifier: Programming Language :: Python :: 3
Classifier: Programming Language :: Python
Classifier: Intended Audience :: Developers
Classifier: Intended Audience :: Information Technology
Classifier: Intended Audience :: System Administrators
Classifier: License :: OSI Approved :: BSD License
Classifier: Topic :: System :: Networking
Requires-Python: >=3.10
License-File: LICENSE
Requires-Dist: typer
Requires-Dist: rich
Requires-Dist: SOLIDserverRest>=2.9.6
Dynamic: author
Dynamic: author-email
Dynamic: classifier
Dynamic: description
Dynamic: description-content-type
Dynamic: home-page
Dynamic: license
Dynamic: license-file
Dynamic: project-url
Dynamic: requires-dist
Dynamic: requires-python
Dynamic: summary
